nanox/__init__.py
nanox/model/__init__.py
nanox/model/encoder.py
nanox/model/encoder_layer.py
nanox/model/layers.py
nanox/model/multihead_attention.py
nanox/model/pretained.py
nanox/nanox.py
nanox-0.1.1.dist-info/LICENSE
nanox-0.1.1.dist-info/WHEEL
nanox-0.1.1.dist-info/METADATA
nanox-0.1.1.dist-info/RECORD
