Metadata-Version: 2.1
Name: nanox
Version: 0.1.1
Summary: A transformer model for creating bio-compatible nanomachines
Author: Kye Gomez
Author-email: kye@apac.ai
Requires-Python: >=3.8,<4.0
Classifier: Programming Language :: Python :: 3
Classifier: Programming Language :: Python :: 3.8
Classifier: Programming Language :: Python :: 3.9
Classifier: Programming Language :: Python :: 3.10
Classifier: Programming Language :: Python :: 3.11
Requires-Dist: torch (>=1.10.0,<2.0.0)
